livemaker/.gitignore
livemaker/GalImagePlugin.py
livemaker/__init__.py
livemaker/_version.py
livemaker/archive.py
livemaker/exceptions.py
livemaker/lpb.py
livemaker/lpm.py
livemaker/project.py
livemaker/scramble.py
livemaker/cli/__init__.py
livemaker/cli/cli.py
livemaker/cli/lmar.py
livemaker/cli/lmgraph.py
livemaker/cli/lmlpb.py
livemaker/cli/lmlsb.py
livemaker/cli/lmpatch.py
livemaker/lsb/__init__.py
livemaker/lsb/command.py
livemaker/lsb/core.py
livemaker/lsb/graph.py
livemaker/lsb/lmscript.py
livemaker/lsb/menu.py
livemaker/lsb/novel.py
livemaker/lsb/translate.py
pylivemaker-1.2.1.dist-info/AUTHORS.rst
pylivemaker-1.2.1.dist-info/COPYING
pylivemaker-1.2.1.dist-info/METADATA
pylivemaker-1.2.1.dist-info/WHEEL
pylivemaker-1.2.1.dist-info/entry_points.txt
pylivemaker-1.2.1.dist-info/top_level.txt
pylivemaker-1.2.1.dist-info/RECORD
