Metadata-Version: 2.1
Name: pylivemaker
Version: 1.2.1
Summary: Python package for manipulating LiveMaker game resources.
Author: tinfoil
Author-email: Peter Rowlands <peter@pmrowla.com>
License: GNU General Public License v3 or later (GPLv3+)
Project-URL: documentation, https://pylivemaker.readthedocs.io/en/latest/
Project-URL: repository, https://github.com/pmrowla/pylivemaker
Project-URL: changelog, https://github.com/pmrowla/pylivemaker/blob/master/HISTORY.rst
Keywords: LiveMaker
Classifier: Development Status :: 5 - Production/Stable
Classifier: Intended Audience :: Developers
Classifier: License :: OSI Approved :: GNU General Public License v3 or later (GPLv3+)
Classifier: Natural Language :: English
Classifier: Programming Language :: Python :: 3
Classifier: Programming Language :: Python :: 3.8
Classifier: Programming Language :: Python :: 3.9
Classifier: Programming Language :: Python :: 3.10
Classifier: Programming Language :: Python :: 3.11
Requires-Python: >=3.8
License-File: COPYING
License-File: AUTHORS.rst
Requires-Dist: Click>=8.1
Requires-Dist: construct<2.11,>=2.10
Requires-Dist: funcy>=1.4
Requires-Dist: loguru>=0.4.1
Requires-Dist: lxml>=4.3
Requires-Dist: networkx>=2.4
Requires-Dist: numpy>=1.16
Requires-Dist: Pillow>=10.2.0
Requires-Dist: pydot>=1.4.1
Provides-Extra: test
Requires-Dist: coverage>=7; extra == "test"
Requires-Dist: pytest>=5; extra == "test"
Requires-Dist: pytest-datadir>=1.3.1; extra == "test"
Requires-Dist: pytest-cov>=4.0.0; extra == "test"
Provides-Extra: docs
Requires-Dist: Sphinx>=6; extra == "docs"
